regimesplit/__init__.py
regimesplit/cli.py
regimesplit/detection.py
regimesplit/plotting.py
regimesplit/report.py
regimesplit/splitter.py
regimesplit/utils.py
regimesplit/templates/report.html.j2
regimesplit-0.1.2.dist-info/METADATA
regimesplit-0.1.2.dist-info/WHEEL
regimesplit-0.1.2.dist-info/entry_points.txt
regimesplit-0.1.2.dist-info/licenses/LICENSE
regimesplit-0.1.2.dist-info/RECORD
