Metadata-Version: 2.4
Name: regimesplit
Version: 0.1.2
Summary: A Python package for regime detection and splitting in time series data
Project-URL: Homepage, https://github.com/nexiath/regimesplit
Project-URL: Repository, https://github.com/nexiath/regimesplit
Author-email: Robin CASSARD <robin.cassard39@gmail.com>
License: MIT
License-File: LICENSE
Classifier: Development Status :: 3 - Alpha
Classifier: Intended Audience :: Developers
Classifier: License :: OSI Approved :: MIT License
Classifier: Programming Language :: Python :: 3
Classifier: Programming Language :: Python :: 3.8
Classifier: Programming Language :: Python :: 3.9
Classifier: Programming Language :: Python :: 3.10
Classifier: Programming Language :: Python :: 3.11
Requires-Python: >=3.8
Requires-Dist: jinja2
Requires-Dist: matplotlib
Requires-Dist: numpy
Requires-Dist: pandas
Requires-Dist: pytest
Requires-Dist: scikit-learn
Requires-Dist: tyro
